{
    "previousClose": 50.749,
    "regularMarketOpen": 51.63,
    "twoHundredDayAverage": 51.442554,
    "trailingAnnualDividendYield": null,
    "payoutRatio": null,
    "volume24Hr": null,
    "regularMarketDayHigh": 52.35,
    "navPrice": 50.96,
    "averageDailyVolume10Day": 16162,
    "totalAssets": 121034064,
    "regularMarketPreviousClose": 50.749,
    "fiftyDayAverage": 54.73088,
    "trailingAnnualDividendRate": null,
    "open": 51.63,
    "averageVolume10days": 16162,
    "expireDate": null,
    "yield": 0.0058999998,
    "algorithm": null,
    "dividendRate": null,
    "exDividendDate": null,
    "beta": null,
    "circulatingSupply": null,
    "startDate": null,
    "regularMarketDayLow": 51.3422,
    "priceHint": 2,
    "currency": "USD",
    "regularMarketVolume": 23000,
    "lastMarket": null,
    "maxSupply": null,
    "openInterest": null,
    "marketCap": null,
    "volumeAllCurrencies": null,
    "strikePrice": null,
    "averageVolume": 15539,
    "priceToSalesTrailing12Months": null,
    "dayLow": 51.3422,
    "ask": 0,
    "ytdReturn": null,
    "askSize": 900,
    "volume": 23000,
    "fiftyTwoWeekHigh": 57.51,
    "forwardPE": null,
    "maxAge": 1,
    "fromCurrency": null,
    "fiveYearAvgDividendYield": null,
    "fiftyTwoWeekLow": 44.09,
    "bid": 0,
    "tradeable": true,
    "dividendYield": null,
    "bidSize": 900,
    "dayHigh": 52.35,
    "exchange": "PCX",
    "shortName": "AdvisorShares Dorsey Wright",
    "longName": "AdvisorShares Dorsey Wright ADR ETF",
    "exchangeTimezoneName": "America/New_York",
    "exchangeTimezoneShortName": "EST",
    "isEsgPopulated": false,
    "gmtOffSetMilliseconds": "-18000000",
    "quoteType": "ETF",
    "symbol": "AADR",
    "messageBoardId": "finmb_109691817",
    "market": "us_market",
    "annualHoldingsTurnover": null,
    "enterpriseToRevenue": null,
    "beta3Year": 1.18,
    "profitMargins": null,
    "enterpriseToEbitda": null,
    "52WeekChange": null,
    "morningStarRiskRating": null,
    "forwardEps": null,
    "revenueQuarterlyGrowth": null,
    "fundInceptionDate": 1279584000,
    "annualReportExpenseRatio": null,
    "bookValue": null,
    "fundFamily": "AdvisorShares",
    "lastFiscalYearEnd": null,
    "netIncomeToCommon": null,
    "trailingEps": null,
    "lastDividendValue": null,
    "SandP52WeekChange": null,
    "priceToBook": null,
    "nextFiscalYearEnd": null,
    "mostRecentQuarter": null,
    "enterpriseValue": null,
    "threeYearAverageReturn": 0.0448,
    "lastSplitDate": null,
    "lastSplitFactor": null,
    "legalType": "Exchange Traded Fund",
    "morningStarOverallRating": null,
    "earningsQuarterlyGrowth": null,
    "pegRatio": null,
    "lastCapGain": null,
    "category": "Foreign Large Growth",
    "fiveYearAverageReturn": 0.0629,
    "phone": "877-843-3831",
    "longBusinessSummary": "The investment seeks long-term capital appreciation above international benchmarks such as the BNY Mellon Classic ADR Index, the fund&#39;s primary benchmark, and the MSCI EAFE Index, the fund&#39;s secondary benchmark.\n The fund seeks to achieve the fund&#39;s investment objective by selecting primarily a portfolio of U.S.-traded securities of non-U.S. organizations, most often American Depositary Receipts (\"ADRs\"). It will invest at least 80% of its total assets in ADRs and in securities that have economic characteristics similar to ADRs.",
    "companyOfficers": [],
    "regularMarketPrice": 51.63,
    "logo_url": ""
}