{
    "zip": "60014",
    "sector": "Consumer Cyclical",
    "fullTimeEmployees": 14000,
    "longBusinessSummary": "AptarGroup, Inc. provides a range of dispensing, sealing, and packaging solutions primarily for the beauty, personal care, home care, prescription drug, consumer health care, injectable, and food and beverage markets. The company operates through three segments: Beauty + Home, Pharma, and Food + Beverage. The Beauty + Home segment primarily sells pumps, closures, aerosol valves, accessories, and sealing solutions to the personal care and home care markets; and pumps and decorative components to the beauty market. The Pharma segment supplies pumps and metered dose inhaler valves for respiratory ailments, such as asthma and chronic obstructive pulmonary diseases in pharmaceutical market. The Food + Beverage segment offers dispensing and non-dispensing closures, elastomeric flow control components, spray pumps, and aerosol valves to the food and beverage markets. It also manufactures and sells elastomeric primary packaging components for injectable market, which include stoppers for infusion, antibiotic, lyophilization, and diagnostic vials; and pre-filled syringe components, such as plungers, needle shields, tip caps and cartridges, and dropper bulbs and syringe plungers. AptarGroup, Inc. sells its products through own sales force, as well as independent representatives and distributors in the United States, Latin America, and Asia. The company has a strategic partnership with PureCycle Technologies LLC to develop ultra-pure recycled polypropylene into dispensing applications. AptarGroup, Inc. was incorporated in 1992 and is headquartered in Crystal Lake, Illinois.",
    "city": "Crystal Lake",
    "phone": "815 477 0424",
    "state": "IL",
    "country": "United States",
    "companyOfficers": [],
    "website": "http://www.aptar.com",
    "maxAge": 1,
    "address1": "265 Exchange Drive",
    "industry": "Packaging & Containers",
    "address2": "Suite 100",
    "previousClose": 102.76,
    "regularMarketOpen": 105.39,
    "twoHundredDayAverage": 115.036026,
    "trailingAnnualDividendYield": 0.013818606,
    "payoutRatio": 0.38799998,
    "volume24Hr": null,
    "regularMarketDayHigh": 107.63,
    "navPrice": null,
    "averageDailyVolume10Day": 520028,
    "totalAssets": null,
    "regularMarketPreviousClose": 102.76,
    "fiftyDayAverage": 113.76941,
    "trailingAnnualDividendRate": 1.42,
    "open": 105.39,
    "averageVolume10days": 520028,
    "expireDate": null,
    "yield": null,
    "algorithm": null,
    "dividendRate": 1.44,
    "exDividendDate": 1580169600,
    "beta": 0.655477,
    "circulatingSupply": null,
    "startDate": null,
    "regularMarketDayLow": 104.44,
    "priceHint": 2,
    "currency": "USD",
    "trailingPE": 29.355192,
    "regularMarketVolume": 291059,
    "lastMarket": null,
    "maxSupply": null,
    "openInterest": null,
    "marketCap": 6881972736,
    "volumeAllCurrencies": null,
    "strikePrice": null,
    "averageVolume": 279378,
    "priceToSalesTrailing12Months": 2.4065096,
    "dayLow": 104.44,
    "ask": 107.47,
    "ytdReturn": null,
    "askSize": 1100,
    "volume": 291059,
    "fiftyTwoWeekHigh": 126.2,
    "forwardPE": 24.473804,
    "fromCurrency": null,
    "fiveYearAvgDividendYield": 1.46,
    "fiftyTwoWeekLow": 99.21,
    "bid": 107.3,
    "tradeable": true,
    "dividendYield": 0.0139999995,
    "bidSize": 900,
    "dayHigh": 107.63,
    "exchange": "NYQ",
    "shortName": "AptarGroup, Inc.",
    "longName": "AptarGroup, Inc.",
    "exchangeTimezoneName": "America/New_York",
    "exchangeTimezoneShortName": "EST",
    "isEsgPopulated": false,
    "gmtOffSetMilliseconds": "-18000000",
    "quoteType": "EQUITY",
    "symbol": "ATR",
    "messageBoardId": "finmb_326230",
    "market": "us_market",
    "annualHoldingsTurnover": null,
    "enterpriseToRevenue": 2.66,
    "beta3Year": null,
    "profitMargins": 0.08469,
    "enterpriseToEbitda": 12.881,
    "52WeekChange": 0.022589326,
    "morningStarRiskRating": null,
    "forwardEps": 4.39,
    "revenueQuarterlyGrowth": null,
    "sharesOutstanding": 63927100,
    "fundInceptionDate": null,
    "annualReportExpenseRatio": null,
    "bookValue": 24.649,
    "sharesShort": 932101,
    "sharesPercentSharesOut": 0.0146,
    "fundFamily": null,
    "lastFiscalYearEnd": 1577750400,
    "heldPercentInstitutions": 0.90742993,
    "netIncomeToCommon": 242202000,
    "trailingEps": 3.66,
    "lastDividendValue": null,
    "SandP52WeekChange": 0.08368194,
    "priceToBook": 4.3587976,
    "heldPercentInsiders": 0.0061500003,
    "nextFiscalYearEnd": 1640908800,
    "mostRecentQuarter": 1577750400,
    "shortRatio": 4.22,
    "sharesShortPreviousMonthDate": 1579046400,
    "floatShares": 63604478,
    "enterpriseValue": 7608123392,
    "threeYearAverageReturn": null,
    "lastSplitDate": 1178755200,
    "lastSplitFactor": "2:1",
    "legalType": null,
    "morningStarOverallRating": null,
    "earningsQuarterlyGrowth": 0.193,
    "dateShortInterest": 1581638400,
    "pegRatio": 4.21,
    "lastCapGain": null,
    "shortPercentOfFloat": 0.0194,
    "sharesShortPriorMonth": 766205,
    "category": null,
    "fiveYearAverageReturn": null,
    "regularMarketPrice": 105.39,
    "logo_url": "https://logo.clearbit.com/aptar.com"
}