{
    "zip": "19809",
    "sector": "Financial Services",
    "longBusinessSummary": "BlackRock Municipal Income Quality Trust is a closed-ended fixed income mutual fund launched by BlackRock, Inc. It is managed by BlackRock Advisors, LLC. The fund invests in the fixed income markets of the United States. It primarily invests in investment grade municipal bonds exempt from federal income taxes, including the alternative minimum tax. BlackRock Municipal Income Quality Trust was formed on October 31, 2002 and is domiciled in the United States.",
    "city": "Wilmington",
    "phone": "302-797-2000",
    "state": "DE",
    "country": "United States",
    "companyOfficers": [],
    "website": "http://www.blackrock.com/investing/products/240256/blackrock-insured-municipal-income-trust-usd-fund",
    "maxAge": 1,
    "address1": "100 Bellevue Parkway",
    "fax": "302-797-2473",
    "industry": "Asset Management",
    "previousClose": 14.6,
    "regularMarketOpen": 14.72,
    "twoHundredDayAverage": 14.16022,
    "trailingAnnualDividendYield": 0.04219178,
    "payoutRatio": 0.3709,
    "volume24Hr": null,
    "regularMarketDayHigh": 14.72,
    "navPrice": null,
    "averageDailyVolume10Day": 77742,
    "totalAssets": null,
    "regularMarketPreviousClose": 14.6,
    "fiftyDayAverage": 14.511176,
    "trailingAnnualDividendRate": 0.616,
    "open": 14.72,
    "averageVolume10days": 77742,
    "expireDate": null,
    "yield": null,
    "algorithm": null,
    "dividendRate": 0.58,
    "exDividendDate": 1584057600,
    "beta": 0.137809,
    "circulatingSupply": null,
    "startDate": null,
    "regularMarketDayLow": 14.495,
    "priceHint": 2,
    "currency": "USD",
    "trailingPE": 8.818182,
    "regularMarketVolume": 69285,
    "lastMarket": null,
    "maxSupply": null,
    "openInterest": null,
    "marketCap": 384211680,
    "volumeAllCurrencies": null,
    "strikePrice": null,
    "averageVolume": 44852,
    "priceToSalesTrailing12Months": 14.738114,
    "dayLow": 14.495,
    "ask": 14.56,
    "ytdReturn": null,
    "askSize": 3200,
    "volume": 69285,
    "fiftyTwoWeekHigh": 14.72,
    "forwardPE": null,
    "fromCurrency": null,
    "fiveYearAvgDividendYield": 5.33,
    "fiftyTwoWeekLow": 13.21,
    "bid": 14.52,
    "tradeable": true,
    "dividendYield": 0.0395,
    "bidSize": 2200,
    "dayHigh": 14.72,
    "exchange": "NYQ",
    "shortName": "42514",
    "longName": "BlackRock Municipal Income Quality Trust",
    "exchangeTimezoneName": "America/New_York",
    "exchangeTimezoneShortName": "EST",
    "isEsgPopulated": false,
    "gmtOffSetMilliseconds": "-18000000",
    "quoteType": "EQUITY",
    "symbol": "BYM",
    "messageBoardId": "finmb_3606418",
    "market": "us_market",
    "annualHoldingsTurnover": null,
    "enterpriseToRevenue": 24.601,
    "beta3Year": null,
    "profitMargins": 1.6716499,
    "enterpriseToEbitda": null,
    "52WeekChange": 0.09527385,
    "morningStarRiskRating": null,
    "forwardEps": null,
    "revenueQuarterlyGrowth": null,
    "sharesOutstanding": 26406300,
    "fundInceptionDate": null,
    "annualReportExpenseRatio": null,
    "bookValue": 15.721,
    "sharesShort": 9946,
    "sharesPercentSharesOut": 0.0004,
    "fundFamily": null,
    "lastFiscalYearEnd": 1567209600,
    "heldPercentInstitutions": 0.31726,
    "netIncomeToCommon": 43578560,
    "trailingEps": 1.65,
    "lastDividendValue": null,
    "SandP52WeekChange": 0.08368194,
    "priceToBook": 0.9255137,
    "heldPercentInsiders": 2.0000001e-05,
    "nextFiscalYearEnd": 1630368000,
    "mostRecentQuarter": 1567209600,
    "shortRatio": 0.62,
    "sharesShortPreviousMonthDate": 1579046400,
    "floatShares": null,
    "enterpriseValue": 641326272,
    "threeYearAverageReturn": null,
    "lastSplitDate": null,
    "lastSplitFactor": null,
    "legalType": null,
    "morningStarOverallRating": null,
    "earningsQuarterlyGrowth": 4.457,
    "dateShortInterest": 1581638400,
    "pegRatio": null,
    "lastCapGain": null,
    "shortPercentOfFloat": null,
    "sharesShortPriorMonth": 5223,
    "category": null,
    "fiveYearAverageReturn": null,
    "regularMarketPrice": 14.72,
    "logo_url": "https://logo.clearbit.com/blackrock.com"
}