{
    "zip": "20850",
    "sector": "Consumer Cyclical",
    "longBusinessSummary": "Choice Hotels International, Inc., together with its subsidiaries, operates as a hotel franchisor worldwide. It operates through Hotel Franchising and Corporate & Other segments. The company franchises lodging properties under the brand names of Comfort Inn, Comfort Suites, Quality, Clarion, Clarion Pointe, Sleep Inn, Econo Lodge, Rodeway Inn, MainStay Suites, Suburban Extended Stay Hotel, WoodSpring Suites, Cambria Hotels, V8 Hotel K\u00f6ln @Motorworld, Quality Hotel Ostrava, Hotel Aquarius Venice, and Ascend Hotel Collection. It also develops and markets cloud-based technology products to the hotel industry. As of February 12, 2020, the company had approximately 7,000 hotels with 575,000 rooms in approximately 40 countries and territories. Choice Hotels International, Inc. has a strategic agreement with AM Resorts, LLC to improve its loyalty program. The company was founded in 1939 and is based in Rockville, Maryland.",
    "city": "Rockville",
    "phone": "301-592-5000",
    "state": "MD",
    "country": "United States",
    "companyOfficers": [],
    "website": "http://www.choicehotels.com",
    "maxAge": 1,
    "address1": "1 Choice Hotels Circle",
    "industry": "Lodging",
    "address2": "Suite 400",
    "previousClose": 91.71,
    "regularMarketOpen": 93.36,
    "twoHundredDayAverage": 95.175476,
    "trailingAnnualDividendYield": 0.009486425,
    "payoutRatio": 0.2186,
    "volume24Hr": null,
    "regularMarketDayHigh": 93.36,
    "navPrice": null,
    "averageDailyVolume10Day": 595687,
    "totalAssets": null,
    "regularMarketPreviousClose": 91.71,
    "fiftyDayAverage": 100.805885,
    "trailingAnnualDividendRate": 0.87,
    "open": 93.36,
    "averageVolume10days": 595687,
    "expireDate": null,
    "yield": null,
    "algorithm": null,
    "dividendRate": 0.9,
    "exDividendDate": 1585699200,
    "beta": 0.962014,
    "circulatingSupply": null,
    "startDate": null,
    "regularMarketDayLow": 90.51,
    "priceHint": 2,
    "currency": "USD",
    "trailingPE": 23.273869,
    "regularMarketVolume": 469981,
    "lastMarket": null,
    "maxSupply": null,
    "openInterest": null,
    "marketCap": 5162334720,
    "volumeAllCurrencies": null,
    "strikePrice": null,
    "averageVolume": 642778,
    "priceToSalesTrailing12Months": 4.6306443,
    "dayLow": 90.51,
    "ask": 92.63,
    "ytdReturn": null,
    "askSize": 1100,
    "volume": 469981,
    "fiftyTwoWeekHigh": 109.26,
    "forwardPE": 20.093275,
    "fromCurrency": null,
    "fiveYearAvgDividendYield": 1.28,
    "fiftyTwoWeekLow": 76.2,
    "bid": 92.59,
    "tradeable": true,
    "dividendYield": 0.0095,
    "bidSize": 1200,
    "dayHigh": 93.36,
    "exchange": "NYQ",
    "shortName": "Choice Hotels International, In",
    "longName": "Choice Hotels International, Inc.",
    "exchangeTimezoneName": "America/New_York",
    "exchangeTimezoneShortName": "EST",
    "isEsgPopulated": false,
    "gmtOffSetMilliseconds": "-18000000",
    "quoteType": "EQUITY",
    "symbol": "CHH",
    "messageBoardId": "finmb_370714",
    "market": "us_market",
    "annualHoldingsTurnover": null,
    "enterpriseToRevenue": 5.449,
    "beta3Year": null,
    "profitMargins": 0.19992,
    "enterpriseToEbitda": 16.365,
    "52WeekChange": 0.13544631,
    "morningStarRiskRating": null,
    "forwardEps": 4.61,
    "revenueQuarterlyGrowth": null,
    "sharesOutstanding": 55730700,
    "fundInceptionDate": null,
    "annualReportExpenseRatio": null,
    "bookValue": -0.424,
    "sharesShort": 4165394,
    "sharesPercentSharesOut": 0.0747,
    "fundFamily": null,
    "lastFiscalYearEnd": 1577750400,
    "heldPercentInstitutions": 0.64014,
    "netIncomeToCommon": 222878000,
    "trailingEps": 3.98,
    "lastDividendValue": null,
    "SandP52WeekChange": 0.08368194,
    "priceToBook": null,
    "heldPercentInsiders": 0.37855998,
    "nextFiscalYearEnd": 1640908800,
    "mostRecentQuarter": 1577750400,
    "shortRatio": 9.05,
    "sharesShortPreviousMonthDate": 1579046400,
    "floatShares": 45170767,
    "enterpriseValue": 6074176512,
    "threeYearAverageReturn": null,
    "lastSplitDate": 1130112000,
    "lastSplitFactor": "2:1",
    "legalType": null,
    "morningStarOverallRating": null,
    "earningsQuarterlyGrowth": 0.34,
    "dateShortInterest": 1581638400,
    "pegRatio": 5.31,
    "lastCapGain": null,
    "shortPercentOfFloat": 0.124,
    "sharesShortPriorMonth": 4335576,
    "category": null,
    "fiveYearAverageReturn": null,
    "regularMarketPrice": 93.36,
    "logo_url": "https://logo.clearbit.com/choicehotels.com"
}