{
    "zip": "10022",
    "sector": "Consumer Defensive",
    "fullTimeEmployees": 34300,
    "longBusinessSummary": "Colgate-Palmolive Company operates as a consumer products company worldwide. The company operates through two segments, Oral, Personal and Home Care; and Pet Nutrition. It offers oral care products, including toothpastes, toothbrushes, and mouthwashes, as well as pharmaceutical products for dentists and other oral health professionals; and personal care products, such as liquid hand soaps, bar soaps, shower gels, deodorants and antiperspirants, skin health products, and shampoos and conditioners. The company also provides home care products comprising dishwashing liquids, household cleaners, and fabric conditioners; pet nutrition products for everyday nutritional needs; and a range of therapeutic products to manage disease conditions in dogs and cats. Its principal trademarks include Colgate, Palmolive, elmex, meridol, Tom's of Maine, Sorriso, Hello, Speed Stick, Lady Speed Stick, Softsoap, Irish Spring, Protex, Sanex, Filorga, Elta MD, PCA Skin, Ajax, Axion, Fabuloso, Soupline, and Suavitel, as well as Hill's Science Diet and Hill's Prescription Diet. The company markets and sells its oral, personal, and home care products to various traditional and eCommerce retailers, wholesalers, and distributors; and pet nutrition products for dogs and cats through pet supply retailers, veterinarians, and e-commerce retailers. Colgate-Palmolive Company was founded in 1806 and is headquartered in New York, New York.",
    "city": "New York",
    "phone": "212 310 2000",
    "state": "NY",
    "country": "United States",
    "companyOfficers": [],
    "website": "http://www.colgatepalmolive.com",
    "maxAge": 1,
    "address1": "300 Park Avenue",
    "industry": "Household & Personal Products",
    "previousClose": 71.78,
    "regularMarketOpen": 73.9,
    "twoHundredDayAverage": 70.43235,
    "trailingAnnualDividendYield": 0.023822792,
    "payoutRatio": 0.6218,
    "volume24Hr": null,
    "regularMarketDayHigh": 75.47,
    "navPrice": null,
    "averageDailyVolume10Day": 6893314,
    "totalAssets": null,
    "regularMarketPreviousClose": 71.78,
    "fiftyDayAverage": 73.077354,
    "trailingAnnualDividendRate": 1.71,
    "open": 73.9,
    "averageVolume10days": 6893314,
    "expireDate": null,
    "yield": null,
    "algorithm": null,
    "dividendRate": 1.72,
    "exDividendDate": 1579651200,
    "beta": 0.680212,
    "circulatingSupply": null,
    "startDate": null,
    "regularMarketDayLow": 73.01,
    "priceHint": 2,
    "currency": "USD",
    "trailingPE": 27.407274,
    "regularMarketVolume": 6885875,
    "lastMarket": null,
    "maxSupply": null,
    "openInterest": null,
    "marketCap": 64443613184,
    "volumeAllCurrencies": null,
    "strikePrice": null,
    "averageVolume": 4320427,
    "priceToSalesTrailing12Months": 4.1065197,
    "dayLow": 73.01,
    "ask": 0,
    "ytdReturn": null,
    "askSize": 1000,
    "volume": 6885875,
    "fiftyTwoWeekHigh": 77.41,
    "forwardPE": 23.851267,
    "fromCurrency": null,
    "fiveYearAvgDividendYield": 2.31,
    "fiftyTwoWeekLow": 64.75,
    "bid": 0,
    "tradeable": true,
    "dividendYield": 0.024,
    "bidSize": 1000,
    "dayHigh": 75.47,
    "exchange": "NYQ",
    "shortName": "Colgate-Palmolive Company",
    "longName": "Colgate-Palmolive Company",
    "exchangeTimezoneName": "America/New_York",
    "exchangeTimezoneShortName": "EST",
    "isEsgPopulated": false,
    "gmtOffSetMilliseconds": "-18000000",
    "quoteType": "EQUITY",
    "symbol": "CL",
    "messageBoardId": "finmb_53837907",
    "market": "us_market",
    "annualHoldingsTurnover": null,
    "enterpriseToRevenue": 4.434,
    "beta3Year": null,
    "profitMargins": 0.15083,
    "enterpriseToEbitda": 17.374,
    "52WeekChange": 0.09404051,
    "morningStarRiskRating": null,
    "forwardEps": 3.16,
    "revenueQuarterlyGrowth": null,
    "sharesOutstanding": 857043968,
    "fundInceptionDate": null,
    "annualReportExpenseRatio": null,
    "bookValue": 0.137,
    "sharesShort": 12183090,
    "sharesPercentSharesOut": 0.014199999,
    "fundFamily": null,
    "lastFiscalYearEnd": 1577750400,
    "heldPercentInstitutions": 0.81537,
    "netIncomeToCommon": 2367000064,
    "trailingEps": 2.75,
    "lastDividendValue": null,
    "SandP52WeekChange": 0.08368194,
    "priceToBook": 550.14606,
    "heldPercentInsiders": 0.00319,
    "nextFiscalYearEnd": 1640908800,
    "mostRecentQuarter": 1577750400,
    "shortRatio": 2.82,
    "sharesShortPreviousMonthDate": 1579046400,
    "floatShares": 795365799,
    "enterpriseValue": 69581733888,
    "threeYearAverageReturn": null,
    "lastSplitDate": 1368662400,
    "lastSplitFactor": "2:1",
    "legalType": null,
    "morningStarOverallRating": null,
    "earningsQuarterlyGrowth": 0.061,
    "dateShortInterest": 1581638400,
    "pegRatio": 4.07,
    "lastCapGain": null,
    "shortPercentOfFloat": 0.0152,
    "sharesShortPriorMonth": 13914801,
    "category": null,
    "fiveYearAverageReturn": null,
    "regularMarketPrice": 73.9,
    "logo_url": "https://logo.clearbit.com/colgatepalmolive.com"
}