{
    "zip": "73102",
    "sector": "Energy",
    "fullTimeEmployees": 1260,
    "longBusinessSummary": "Continental Resources, Inc. explores for, develops, and produces crude oil and natural gas properties primarily in the north, south, and east regions of the United States. The company sells its crude oil and natural gas production to energy marketing companies, crude oil refining companies, and natural gas gathering and processing companies. As of December 31, 2019, its proved reserves were 1,619 million barrels of crude oil equivalent (MMBoe) with estimated proved developed reserves of 707 MMBoe. Continental Resources, Inc. was founded in 1967 and is based in Oklahoma City, Oklahoma.",
    "city": "Oklahoma City",
    "phone": "405 234 9000",
    "state": "OK",
    "country": "United States",
    "companyOfficers": [],
    "website": "http://www.clr.com",
    "maxAge": 1,
    "address1": "20 North Broadway",
    "fax": "405 234 9253",
    "industry": "Oil & Gas E&P",
    "previousClose": 17.43,
    "regularMarketOpen": 18.01,
    "twoHundredDayAverage": 30.13927,
    "trailingAnnualDividendYield": 0.0028686174,
    "payoutRatio": 0.024,
    "volume24Hr": null,
    "regularMarketDayHigh": 18.2801,
    "navPrice": null,
    "averageDailyVolume10Day": 6550175,
    "totalAssets": null,
    "regularMarketPreviousClose": 17.43,
    "fiftyDayAverage": 26.175589,
    "trailingAnnualDividendRate": 0.05,
    "open": 18.01,
    "averageVolume10days": 6550175,
    "expireDate": null,
    "yield": null,
    "algorithm": null,
    "dividendRate": 0.2,
    "exDividendDate": 1580947200,
    "beta": 2.020318,
    "circulatingSupply": null,
    "startDate": null,
    "regularMarketDayLow": 17.11,
    "priceHint": 2,
    "currency": "USD",
    "trailingPE": 8.548078,
    "regularMarketVolume": 6120976,
    "lastMarket": null,
    "maxSupply": null,
    "openInterest": null,
    "marketCap": 6605999104,
    "volumeAllCurrencies": null,
    "strikePrice": null,
    "averageVolume": 3091985,
    "priceToSalesTrailing12Months": 1.563596,
    "dayLow": 17.11,
    "ask": 18.18,
    "ytdReturn": null,
    "askSize": 900,
    "volume": 6120976,
    "fiftyTwoWeekHigh": 52.04,
    "forwardPE": 7.169355,
    "fromCurrency": null,
    "fiveYearAvgDividendYield": null,
    "fiftyTwoWeekLow": 14.77,
    "bid": 0,
    "tradeable": true,
    "dividendYield": 0.0111,
    "bidSize": 900,
    "dayHigh": 18.2801,
    "exchange": "NYQ",
    "shortName": "Continental Resources, Inc.",
    "longName": "Continental Resources, Inc.",
    "exchangeTimezoneName": "America/New_York",
    "exchangeTimezoneShortName": "EST",
    "isEsgPopulated": false,
    "gmtOffSetMilliseconds": "-18000000",
    "quoteType": "EQUITY",
    "symbol": "CLR",
    "messageBoardId": "finmb_1534795",
    "market": "us_market",
    "annualHoldingsTurnover": null,
    "enterpriseToRevenue": 2.859,
    "beta3Year": null,
    "profitMargins": 0.18359,
    "enterpriseToEbitda": 3.592,
    "52WeekChange": -0.5909411,
    "morningStarRiskRating": null,
    "forwardEps": 2.48,
    "revenueQuarterlyGrowth": null,
    "sharesOutstanding": 371540992,
    "fundInceptionDate": null,
    "annualReportExpenseRatio": null,
    "bookValue": 18.339,
    "sharesShort": 4863838,
    "sharesPercentSharesOut": 0.013099999,
    "fundFamily": null,
    "lastFiscalYearEnd": 1577750400,
    "heldPercentInstitutions": 0.04526,
    "netIncomeToCommon": 775641024,
    "trailingEps": 2.08,
    "lastDividendValue": null,
    "SandP52WeekChange": 0.08368194,
    "priceToBook": 0.96951854,
    "heldPercentInsiders": 0.63189,
    "nextFiscalYearEnd": 1640908800,
    "mostRecentQuarter": 1577750400,
    "shortRatio": 1.41,
    "sharesShortPreviousMonthDate": 1579046400,
    "floatShares": 77620561,
    "enterpriseValue": 12078547968,
    "threeYearAverageReturn": null,
    "lastSplitDate": 1410393600,
    "lastSplitFactor": "2:1",
    "legalType": null,
    "morningStarOverallRating": null,
    "earningsQuarterlyGrowth": -0.019,
    "dateShortInterest": 1581638400,
    "pegRatio": -2.45,
    "lastCapGain": null,
    "shortPercentOfFloat": 0.056199998,
    "sharesShortPriorMonth": 4647731,
    "category": null,
    "fiveYearAverageReturn": null,
    "regularMarketPrice": 18.01,
    "logo_url": "https://logo.clearbit.com/clr.com"
}