{
    "previousClose": 113.5,
    "regularMarketOpen": 113.57,
    "twoHundredDayAverage": 110.23306,
    "trailingAnnualDividendYield": null,
    "payoutRatio": null,
    "volume24Hr": null,
    "regularMarketDayHigh": 114.24,
    "navPrice": 113.77,
    "averageDailyVolume10Day": 78925,
    "totalAssets": 643906240,
    "regularMarketPreviousClose": 113.5,
    "fiftyDayAverage": 112.14147,
    "trailingAnnualDividendRate": null,
    "open": 113.57,
    "averageVolume10days": 78925,
    "expireDate": null,
    "yield": 0.0318,
    "algorithm": null,
    "dividendRate": null,
    "exDividendDate": null,
    "beta": null,
    "circulatingSupply": null,
    "startDate": null,
    "regularMarketDayLow": 113.57,
    "priceHint": 2,
    "currency": "USD",
    "regularMarketVolume": 21890,
    "lastMarket": null,
    "maxSupply": null,
    "openInterest": null,
    "marketCap": null,
    "volumeAllCurrencies": null,
    "strikePrice": null,
    "averageVolume": 43354,
    "priceToSalesTrailing12Months": null,
    "dayLow": 113.57,
    "ask": 114.14,
    "ytdReturn": null,
    "askSize": 900,
    "volume": 21890,
    "fiftyTwoWeekHigh": 114.24,
    "forwardPE": null,
    "maxAge": 1,
    "fromCurrency": null,
    "fiveYearAvgDividendYield": null,
    "fiftyTwoWeekLow": 101.3,
    "bid": 113.87,
    "tradeable": true,
    "dividendYield": null,
    "bidSize": 900,
    "dayHigh": 114.24,
    "exchange": "PCX",
    "shortName": "Pimco Investment Grade Corporat",
    "longName": "PIMCO Investment Grade Corporate Bond Index Exchange-Traded Fund",
    "exchangeTimezoneName": "America/New_York",
    "exchangeTimezoneShortName": "EST",
    "isEsgPopulated": false,
    "gmtOffSetMilliseconds": "-18000000",
    "quoteType": "ETF",
    "symbol": "CORP",
    "messageBoardId": "finmb_113633190",
    "market": "us_market",
    "annualHoldingsTurnover": null,
    "enterpriseToRevenue": null,
    "beta3Year": 1.12,
    "profitMargins": null,
    "enterpriseToEbitda": null,
    "52WeekChange": null,
    "morningStarRiskRating": null,
    "forwardEps": null,
    "revenueQuarterlyGrowth": null,
    "fundInceptionDate": 1284940800,
    "annualReportExpenseRatio": null,
    "bookValue": null,
    "fundFamily": "PIMCO",
    "lastFiscalYearEnd": null,
    "netIncomeToCommon": null,
    "trailingEps": null,
    "lastDividendValue": null,
    "SandP52WeekChange": null,
    "priceToBook": null,
    "nextFiscalYearEnd": null,
    "mostRecentQuarter": null,
    "enterpriseValue": null,
    "threeYearAverageReturn": 0.0694,
    "lastSplitDate": null,
    "lastSplitFactor": null,
    "legalType": "Exchange Traded Fund",
    "morningStarOverallRating": null,
    "earningsQuarterlyGrowth": null,
    "pegRatio": null,
    "lastCapGain": null,
    "category": "Corporate Bond",
    "fiveYearAverageReturn": 0.051999997,
    "phone": "888-400-4383",
    "longBusinessSummary": "The investment seeks to provide total return that closely corresponds, before fees and expenses, to the total return of the ICE BofAML US Corporate Index.\n The fund invests at least 80% of its total assets (exclusive of collateral held from securities lending) in the component securities of the ICE BofAML US Corporate Index (the \"underlying index\"). The underlying index is an unmanaged index comprised of U.S. dollar denominated investment grade corporate debt securities publicly issued in the U.S. domestic market with at least one year remaining term to final maturity.",
    "companyOfficers": [],
    "regularMarketPrice": 113.57,
    "logo_url": ""
}