{
    "previousClose": 25.0441,
    "regularMarketOpen": 25.3,
    "twoHundredDayAverage": 25.137226,
    "trailingAnnualDividendYield": null,
    "payoutRatio": null,
    "volume24Hr": null,
    "regularMarketDayHigh": 25.3,
    "navPrice": 25.22,
    "averageDailyVolume10Day": 2137,
    "totalAssets": 26420140,
    "regularMarketPreviousClose": 25.0441,
    "fiftyDayAverage": 25.123236,
    "trailingAnnualDividendRate": null,
    "open": 25.3,
    "averageVolume10days": 2137,
    "expireDate": null,
    "yield": 0.020299999,
    "algorithm": null,
    "dividendRate": null,
    "exDividendDate": null,
    "beta": null,
    "circulatingSupply": null,
    "startDate": null,
    "regularMarketDayLow": 25.2351,
    "priceHint": 2,
    "currency": "USD",
    "regularMarketVolume": 1584,
    "lastMarket": null,
    "maxSupply": null,
    "openInterest": null,
    "marketCap": null,
    "volumeAllCurrencies": null,
    "strikePrice": null,
    "averageVolume": 1811,
    "priceToSalesTrailing12Months": null,
    "dayLow": 25.2351,
    "ask": 25.55,
    "ytdReturn": null,
    "askSize": 1200,
    "volume": 1584,
    "fiftyTwoWeekHigh": 26.28,
    "forwardPE": null,
    "maxAge": 1,
    "fromCurrency": null,
    "fiveYearAvgDividendYield": null,
    "fiftyTwoWeekLow": 24.6,
    "bid": 25.03,
    "tradeable": true,
    "dividendYield": null,
    "bidSize": 1100,
    "dayHigh": 25.3,
    "exchange": "PCX",
    "shortName": "WisdomTree Chinese Yuan Strateg",
    "longName": "WisdomTree Chinese Yuan Strategy Fund",
    "exchangeTimezoneName": "America/New_York",
    "exchangeTimezoneShortName": "EST",
    "isEsgPopulated": false,
    "gmtOffSetMilliseconds": "-18000000",
    "quoteType": "ETF",
    "symbol": "CYB",
    "messageBoardId": "finmb_44764524",
    "market": "us_market",
    "annualHoldingsTurnover": null,
    "enterpriseToRevenue": null,
    "beta3Year": -7.25,
    "profitMargins": null,
    "enterpriseToEbitda": null,
    "52WeekChange": null,
    "morningStarRiskRating": null,
    "forwardEps": null,
    "revenueQuarterlyGrowth": null,
    "fundInceptionDate": 1210723200,
    "annualReportExpenseRatio": null,
    "bookValue": null,
    "fundFamily": "WisdomTree",
    "lastFiscalYearEnd": null,
    "netIncomeToCommon": null,
    "trailingEps": null,
    "lastDividendValue": null,
    "SandP52WeekChange": null,
    "priceToBook": null,
    "nextFiscalYearEnd": null,
    "mostRecentQuarter": null,
    "enterpriseValue": null,
    "threeYearAverageReturn": 0.0269,
    "lastSplitDate": null,
    "lastSplitFactor": null,
    "legalType": "Exchange Traded Fund",
    "morningStarOverallRating": null,
    "earningsQuarterlyGrowth": null,
    "pegRatio": null,
    "lastCapGain": null,
    "category": "Single Currency",
    "fiveYearAverageReturn": 0.0067000003,
    "phone": "866-909-9473",
    "longBusinessSummary": "The investment seeks to achieve total returns reflective of both money market rates in China available to foreign investors and changes in value of the Chinese yuan relative to the U.S. dollar.\n The fund normally invests at least 80% of its net assets, plus the amount of any borrowings for investment purposes, in investments whose combined performance is economically tied to China. It is an actively managed exchange traded fund (\"ETF\"). The fund generally will maintain a weighted average portfolio maturity of 90 days or less with respect to the money market securities in its portfolio. It is non-diversified.",
    "companyOfficers": [],
    "regularMarketPrice": 25.3,
    "logo_url": ""
}