{
    "previousClose": 38.9,
    "regularMarketOpen": 39.49,
    "twoHundredDayAverage": 42.293797,
    "trailingAnnualDividendYield": null,
    "payoutRatio": null,
    "volume24Hr": null,
    "regularMarketDayHigh": 40.1047,
    "navPrice": 38.9,
    "averageDailyVolume10Day": 563000,
    "totalAssets": 1069442048,
    "regularMarketPreviousClose": 38.9,
    "fiftyDayAverage": 43.498528,
    "trailingAnnualDividendRate": null,
    "open": 39.49,
    "averageVolume10days": 563000,
    "expireDate": null,
    "yield": 0.0222,
    "algorithm": null,
    "dividendRate": null,
    "exDividendDate": null,
    "beta": null,
    "circulatingSupply": null,
    "startDate": null,
    "regularMarketDayLow": 38.84,
    "priceHint": 2,
    "currency": "USD",
    "regularMarketVolume": 418723,
    "lastMarket": null,
    "maxSupply": null,
    "openInterest": null,
    "marketCap": null,
    "volumeAllCurrencies": null,
    "strikePrice": null,
    "averageVolume": 178278,
    "priceToSalesTrailing12Months": null,
    "dayLow": 38.84,
    "ask": 40.31,
    "ytdReturn": null,
    "askSize": 1000,
    "volume": 418723,
    "fiftyTwoWeekHigh": 45.33,
    "forwardPE": null,
    "maxAge": 1,
    "fromCurrency": null,
    "fiveYearAvgDividendYield": null,
    "fiftyTwoWeekLow": 36.55,
    "bid": 39.71,
    "tradeable": true,
    "dividendYield": null,
    "bidSize": 1100,
    "dayHigh": 40.1047,
    "exchange": "PCX",
    "shortName": "Fidelity MSCI Financials Index ",
    "longName": "Fidelity MSCI Financials Index ETF",
    "exchangeTimezoneName": "America/New_York",
    "exchangeTimezoneShortName": "EST",
    "isEsgPopulated": false,
    "gmtOffSetMilliseconds": "-18000000",
    "quoteType": "ETF",
    "symbol": "FNCL",
    "messageBoardId": "finmb_243638581",
    "market": "us_market",
    "annualHoldingsTurnover": null,
    "enterpriseToRevenue": null,
    "beta3Year": 1.16,
    "profitMargins": null,
    "enterpriseToEbitda": null,
    "52WeekChange": null,
    "morningStarRiskRating": null,
    "forwardEps": null,
    "revenueQuarterlyGrowth": null,
    "fundInceptionDate": 1382313600,
    "annualReportExpenseRatio": null,
    "bookValue": null,
    "fundFamily": "Fidelity Investments",
    "lastFiscalYearEnd": null,
    "netIncomeToCommon": null,
    "trailingEps": null,
    "lastDividendValue": null,
    "SandP52WeekChange": null,
    "priceToBook": null,
    "nextFiscalYearEnd": null,
    "mostRecentQuarter": null,
    "enterpriseValue": null,
    "threeYearAverageReturn": 0.0398,
    "lastSplitDate": null,
    "lastSplitFactor": null,
    "legalType": "Exchange Traded Fund",
    "morningStarOverallRating": null,
    "earningsQuarterlyGrowth": null,
    "pegRatio": null,
    "lastCapGain": null,
    "category": "Financial",
    "fiveYearAverageReturn": 0.0828,
    "phone": "800-343-3548",
    "longBusinessSummary": "The investment seeks to provide investment returns that correspond, before fees and expenses, generally to the performance of the MSCI USA IMI Financials Index.\n The fund invests at least 80% of assets in securities included in the fund&#39;s underlying index. The fund&#39;s underlying index is the MSCI USA IMI Financials Index, which represents the performance of the financial sector in the U.S. equity market. It may or may not hold all of the securities in the MSCI USA IMI Financials Index. The fund is non-diversified.",
    "companyOfficers": [],
    "regularMarketPrice": 39.49,
    "logo_url": ""
}