{
    "zip": "98000",
    "sector": "Energy",
    "longBusinessSummary": "GasLog Partners LP owns, operates, and acquires liquefied natural gas (LNG) carriers under multi-year charters. As of October 30, 2019, it operated a fleet of 15 LNG carriers with an average carrying capacity of approximately 158,000 cubic meters. The company was founded in 2014 and is based in Monaco.",
    "city": "Monaco",
    "phone": "377 97 97 51 15",
    "country": "Monaco",
    "companyOfficers": [],
    "website": "http://www.gaslogmlp.com",
    "maxAge": 1,
    "address1": "Gildo Pastor Center",
    "fax": "377 97 97 51 24",
    "industry": "Oil & Gas Midstream",
    "address2": "7 Rue du Gabian",
    "previousClose": 3.63,
    "regularMarketOpen": 3.72,
    "twoHundredDayAverage": 15.297153,
    "trailingAnnualDividendYield": 0.60909086,
    "payoutRatio": null,
    "volume24Hr": null,
    "regularMarketDayHigh": 3.775,
    "navPrice": null,
    "averageDailyVolume10Day": 934137,
    "totalAssets": null,
    "regularMarketPreviousClose": 3.63,
    "fiftyDayAverage": 7.82,
    "trailingAnnualDividendRate": 2.211,
    "open": 3.72,
    "averageVolume10days": 934137,
    "expireDate": null,
    "yield": null,
    "algorithm": null,
    "dividendRate": 0.5,
    "exDividendDate": 1581638400,
    "beta": 1.018551,
    "circulatingSupply": null,
    "startDate": null,
    "regularMarketDayLow": 3.56,
    "priceHint": 4,
    "currency": "USD",
    "regularMarketVolume": 629341,
    "lastMarket": null,
    "maxSupply": null,
    "openInterest": null,
    "marketCap": 179826256,
    "volumeAllCurrencies": null,
    "strikePrice": null,
    "averageVolume": 823637,
    "priceToSalesTrailing12Months": 0.47354478,
    "dayLow": 3.56,
    "ask": 3.61,
    "ytdReturn": null,
    "askSize": 800,
    "volume": 629341,
    "fiftyTwoWeekHigh": 23.145,
    "forwardPE": 3.7978723,
    "fromCurrency": null,
    "fiveYearAvgDividendYield": 10.25,
    "fiftyTwoWeekLow": 3.53,
    "bid": 3.6,
    "tradeable": true,
    "dividendYield": 0.1266,
    "bidSize": 1100,
    "dayHigh": 3.775,
    "exchange": "NYQ",
    "shortName": "GasLog Partners LP",
    "longName": "GasLog Partners LP",
    "exchangeTimezoneName": "America/New_York",
    "exchangeTimezoneShortName": "EST",
    "isEsgPopulated": false,
    "gmtOffSetMilliseconds": "-18000000",
    "quoteType": "EQUITY",
    "symbol": "GLOP",
    "messageBoardId": "finmb_261620021",
    "market": "us_market",
    "annualHoldingsTurnover": null,
    "enterpriseToRevenue": 4.689,
    "beta3Year": null,
    "profitMargins": -0.09156,
    "enterpriseToEbitda": 6.445,
    "52WeekChange": -0.83567226,
    "morningStarRiskRating": null,
    "forwardEps": 0.94,
    "revenueQuarterlyGrowth": null,
    "sharesOutstanding": 46860200,
    "fundInceptionDate": null,
    "annualReportExpenseRatio": null,
    "bookValue": 12.27,
    "sharesShort": 743221,
    "sharesPercentSharesOut": 0.0148,
    "fundFamily": null,
    "lastFiscalYearEnd": 1577750400,
    "heldPercentInstitutions": 0.39294997,
    "netIncomeToCommon": -67747000,
    "trailingEps": -1.345,
    "lastDividendValue": null,
    "SandP52WeekChange": 0.08368194,
    "priceToBook": 0.29095352,
    "heldPercentInsiders": 0.26505,
    "nextFiscalYearEnd": 1640908800,
    "mostRecentQuarter": 1577750400,
    "shortRatio": 0.57,
    "sharesShortPreviousMonthDate": 1579046400,
    "floatShares": 29472375,
    "enterpriseValue": 1780763648,
    "threeYearAverageReturn": null,
    "lastSplitDate": null,
    "lastSplitFactor": null,
    "legalType": null,
    "morningStarOverallRating": null,
    "earningsQuarterlyGrowth": null,
    "dateShortInterest": 1581638400,
    "pegRatio": -0.67,
    "lastCapGain": null,
    "shortPercentOfFloat": 0.0226,
    "sharesShortPriorMonth": 1224659,
    "category": null,
    "fiveYearAverageReturn": null,
    "regularMarketPrice": 3.72,
    "logo_url": "https://logo.clearbit.com/gaslogmlp.com"
}