{
    "previousClose": 234.28,
    "regularMarketOpen": 239.38,
    "twoHundredDayAverage": 229.0751,
    "trailingAnnualDividendYield": 0.0055702575,
    "payoutRatio": null,
    "volume24Hr": null,
    "regularMarketDayHigh": 243.64,
    "navPrice": 234.3,
    "averageDailyVolume10Day": 1288200,
    "totalAssets": 3207916800,
    "regularMarketPreviousClose": 234.28,
    "fiftyDayAverage": 251.95558,
    "trailingAnnualDividendRate": 1.305,
    "open": 239.38,
    "averageVolume10days": 1288200,
    "expireDate": null,
    "yield": 0.0002,
    "algorithm": null,
    "dividendRate": null,
    "exDividendDate": null,
    "beta": null,
    "circulatingSupply": null,
    "startDate": null,
    "regularMarketDayLow": 236.58,
    "priceHint": 2,
    "currency": "USD",
    "trailingPE": 11.671383,
    "regularMarketVolume": 873333,
    "lastMarket": null,
    "maxSupply": null,
    "openInterest": null,
    "marketCap": null,
    "volumeAllCurrencies": null,
    "strikePrice": null,
    "averageVolume": 657319,
    "priceToSalesTrailing12Months": null,
    "dayLow": 236.58,
    "ask": 242.4,
    "ytdReturn": null,
    "askSize": 800,
    "volume": 873333,
    "fiftyTwoWeekHigh": 267.7,
    "forwardPE": null,
    "maxAge": 1,
    "fromCurrency": null,
    "fiveYearAvgDividendYield": null,
    "fiftyTwoWeekLow": 198.32,
    "bid": 0,
    "tradeable": true,
    "dividendYield": null,
    "bidSize": 800,
    "dayHigh": 243.64,
    "exchange": "BTS",
    "shortName": "iShares Expanded Tech-Software ",
    "longName": "iShares Expanded Tech-Software Sector ETF",
    "exchangeTimezoneName": "America/New_York",
    "exchangeTimezoneShortName": "EST",
    "isEsgPopulated": false,
    "gmtOffSetMilliseconds": "-18000000",
    "quoteType": "ETF",
    "symbol": "IGV",
    "messageBoardId": "finmb_8796877",
    "market": "us_market",
    "annualHoldingsTurnover": null,
    "enterpriseToRevenue": null,
    "beta3Year": 1.08,
    "profitMargins": null,
    "enterpriseToEbitda": null,
    "52WeekChange": null,
    "morningStarRiskRating": null,
    "forwardEps": null,
    "revenueQuarterlyGrowth": null,
    "fundInceptionDate": 994723200,
    "annualReportExpenseRatio": null,
    "bookValue": null,
    "fundFamily": "iShares",
    "lastFiscalYearEnd": null,
    "netIncomeToCommon": null,
    "trailingEps": null,
    "lastDividendValue": null,
    "SandP52WeekChange": null,
    "priceToBook": null,
    "nextFiscalYearEnd": null,
    "mostRecentQuarter": null,
    "enterpriseValue": null,
    "threeYearAverageReturn": 0.2534,
    "lastSplitDate": null,
    "lastSplitFactor": null,
    "legalType": "Exchange Traded Fund",
    "morningStarOverallRating": null,
    "earningsQuarterlyGrowth": null,
    "pegRatio": null,
    "lastCapGain": null,
    "category": "Technology",
    "fiveYearAverageReturn": 0.201,
    "phone": "800-474-2737",
    "longBusinessSummary": "The investment seeks to track the investment results of the S&P North American Expanded Technology Software IndexTM.\n The fund generally invests at least 90% of its assets in securities of the underlying index and in depositary receipts representing securities of the underlying index. The index measures the performance of U.S.-traded stocks from the software industry and select companies from the interactive home entertainment and interactive media and services industries in the U.S. and Canada. The fund is non-diversified.",
    "companyOfficers": [],
    "regularMarketPrice": 239.38,
    "logo_url": ""
}