{
    "previousClose": 218.41,
    "regularMarketOpen": 222.04,
    "twoHundredDayAverage": 230.91824,
    "trailingAnnualDividendYield": null,
    "payoutRatio": null,
    "volume24Hr": null,
    "regularMarketDayHigh": 226.9,
    "navPrice": 218.59,
    "averageDailyVolume10Day": 131850,
    "totalAssets": 7373366784,
    "regularMarketPreviousClose": 218.41,
    "fiftyDayAverage": 238.28,
    "trailingAnnualDividendRate": null,
    "open": 222.04,
    "averageVolume10days": 131850,
    "expireDate": null,
    "yield": 0.0111,
    "algorithm": null,
    "dividendRate": null,
    "exDividendDate": null,
    "beta": null,
    "circulatingSupply": null,
    "startDate": null,
    "regularMarketDayLow": 220.96,
    "priceHint": 2,
    "currency": "USD",
    "regularMarketVolume": 83430,
    "lastMarket": null,
    "maxSupply": null,
    "openInterest": null,
    "marketCap": null,
    "volumeAllCurrencies": null,
    "strikePrice": null,
    "averageVolume": 91650,
    "priceToSalesTrailing12Months": null,
    "dayLow": 220.96,
    "ask": 246.18,
    "ytdReturn": null,
    "askSize": 900,
    "volume": 83430,
    "fiftyTwoWeekHigh": 248.43,
    "forwardPE": null,
    "maxAge": 1,
    "fromCurrency": null,
    "fiveYearAvgDividendYield": null,
    "fiftyTwoWeekLow": 209.46,
    "bid": 222.72,
    "tradeable": true,
    "dividendYield": null,
    "bidSize": 1200,
    "dayHigh": 226.9,
    "exchange": "PCX",
    "shortName": "iShares S&P Mid-Cap 400 Growth ",
    "longName": "iShares S&P Mid-Cap 400 Growth ETF",
    "exchangeTimezoneName": "America/New_York",
    "exchangeTimezoneShortName": "EST",
    "isEsgPopulated": false,
    "gmtOffSetMilliseconds": "-18000000",
    "quoteType": "ETF",
    "symbol": "IJK",
    "messageBoardId": "finmb_8798153",
    "market": "us_market",
    "annualHoldingsTurnover": null,
    "enterpriseToRevenue": null,
    "beta3Year": 1.1,
    "profitMargins": null,
    "enterpriseToEbitda": null,
    "52WeekChange": null,
    "morningStarRiskRating": null,
    "forwardEps": null,
    "revenueQuarterlyGrowth": null,
    "fundInceptionDate": 964396800,
    "annualReportExpenseRatio": null,
    "bookValue": null,
    "fundFamily": "iShares",
    "lastFiscalYearEnd": null,
    "netIncomeToCommon": null,
    "trailingEps": null,
    "lastDividendValue": null,
    "SandP52WeekChange": null,
    "priceToBook": null,
    "nextFiscalYearEnd": null,
    "mostRecentQuarter": null,
    "enterpriseValue": null,
    "threeYearAverageReturn": 0.060599998,
    "lastSplitDate": null,
    "lastSplitFactor": null,
    "legalType": "Exchange Traded Fund",
    "morningStarOverallRating": null,
    "earningsQuarterlyGrowth": null,
    "pegRatio": null,
    "lastCapGain": null,
    "category": "Mid-Cap Growth",
    "fiveYearAverageReturn": 0.0675,
    "phone": "800-474-2737",
    "longBusinessSummary": "The investment seeks to track the investment results of the S&P MidCap 400 Growth IndexTM, which measures the performance of the mid-capitalization growth sector of the U.S. equity market.\n The fund generally invests at least 90% of its assets in securities of the underlying index and in depositary receipts representing securities of the underlying index. It may invest the remainder of its assets in certain futures, options and swap contracts, cash and cash equivalents, as well as in securities not included in the underlying index, but which the advisor believes will help the fund track the underlying index.",
    "companyOfficers": [],
    "regularMarketPrice": 222.04,
    "logo_url": ""
}