{
    "previousClose": 21.9957,
    "regularMarketOpen": 22,
    "twoHundredDayAverage": 21.478361,
    "trailingAnnualDividendYield": null,
    "payoutRatio": null,
    "volume24Hr": null,
    "regularMarketDayHigh": 22.0759,
    "navPrice": 22.02,
    "averageDailyVolume10Day": 0,
    "totalAssets": 7539709,
    "regularMarketPreviousClose": 21.9957,
    "fiftyDayAverage": 21.9909,
    "trailingAnnualDividendRate": null,
    "open": 22,
    "averageVolume10days": 0,
    "expireDate": null,
    "yield": 0.0085,
    "algorithm": null,
    "dividendRate": null,
    "exDividendDate": null,
    "beta": null,
    "circulatingSupply": null,
    "startDate": null,
    "regularMarketDayLow": 22,
    "priceHint": 2,
    "currency": "USD",
    "regularMarketVolume": 851,
    "lastMarket": null,
    "maxSupply": null,
    "openInterest": null,
    "marketCap": null,
    "volumeAllCurrencies": null,
    "strikePrice": null,
    "averageVolume": 0,
    "priceToSalesTrailing12Months": null,
    "dayLow": 22,
    "ask": 0,
    "ytdReturn": null,
    "askSize": 2900,
    "volume": 851,
    "fiftyTwoWeekHigh": 22.488,
    "forwardPE": null,
    "maxAge": 1,
    "fromCurrency": null,
    "fiveYearAvgDividendYield": null,
    "fiftyTwoWeekLow": 20.34,
    "bid": 0,
    "tradeable": true,
    "dividendYield": null,
    "bidSize": 900,
    "dayHigh": 22.0759,
    "exchange": "PCX",
    "shortName": "WBI BullBear Rising Income 2000",
    "longName": "WBI BullBear Rising Income 2000 ETF",
    "exchangeTimezoneName": "America/New_York",
    "exchangeTimezoneShortName": "EST",
    "isEsgPopulated": false,
    "gmtOffSetMilliseconds": "-18000000",
    "quoteType": "ETF",
    "symbol": "WBIA",
    "messageBoardId": "finmb_253511557",
    "market": "us_market",
    "annualHoldingsTurnover": null,
    "enterpriseToRevenue": null,
    "beta3Year": 0.86,
    "profitMargins": null,
    "enterpriseToEbitda": null,
    "52WeekChange": null,
    "morningStarRiskRating": null,
    "forwardEps": null,
    "revenueQuarterlyGrowth": null,
    "fundInceptionDate": 1408924800,
    "annualReportExpenseRatio": null,
    "bookValue": null,
    "fundFamily": "WBI Investments",
    "lastFiscalYearEnd": null,
    "netIncomeToCommon": null,
    "trailingEps": null,
    "lastDividendValue": null,
    "SandP52WeekChange": null,
    "priceToBook": null,
    "nextFiscalYearEnd": null,
    "mostRecentQuarter": null,
    "enterpriseValue": null,
    "threeYearAverageReturn": 0.024,
    "lastSplitDate": null,
    "lastSplitFactor": null,
    "legalType": "Exchange Traded Fund",
    "morningStarOverallRating": null,
    "earningsQuarterlyGrowth": null,
    "pegRatio": null,
    "lastCapGain": null,
    "category": "Mid-Cap Blend",
    "fiveYearAverageReturn": -0.0186,
    "phone": "855-924-3837",
    "longBusinessSummary": "The investment seeks long-term capital appreciation and the potential for current income, while also seeking to protect principal during unfavorable market conditions.\n The fund will seek to invest in the equity securities of small-capitalization and mid-capitalization domestic and foreign companies. These securities will be selected on the basis of the Sub-Advisor&#39;s proprietary selection process (\"Selection Process\"). Cash and cash equivalents are some of the investment opportunities evaluated by the Selection Process. It may invest up to 50% of its net assets in the securities of issuers in emerging markets.",
    "companyOfficers": [],
    "regularMarketPrice": 22,
    "logo_url": ""
}